<?xml version="1.0" encoding="utf-8"?><Level xmlns:xsi="http://www.w3.org/2001/XMLSchema-instance" xmlns:xsd="http://www.w3.org/2001/XMLSchema"><Planets><Planet><pos><X>1231.8281</X><Y>285.29602</Y></pos><radius>100</radius><mass>10000</mass><angle>0</angle><typeIndex>5</typeIndex></Planet><Planet><pos><X>4555.8306</X><Y>125.13281</Y></pos><radius>100</radius><mass>10000</mass><angle>0</angle><typeIndex>0</typeIndex></Planet><Planet><pos><X>3407.0554</X><Y>-379.7561</Y></pos><radius>100</radius><mass>10000</mass><angle>0</angle><typeIndex>1</typeIndex></Planet><Planet><pos><X>3817.1345</X><Y>640.718</Y></pos><radius>100</radius><mass>10000</mass><angle>0</angle><typeIndex>0</typeIndex></Planet><Planet><pos><X>5577.3877</X><Y>30.499756</Y></pos><radius>100</radius><mass>10000</mass><angle>0</angle><typeIndex>4</typeIndex></Planet><Planet><pos><X>4440.956</X><Y>254.40356</Y></pos><radius>100</radius><mass>10000</mass><angle>0</angle><typeIndex>0</typeIndex></Planet><Planet><pos><X>1101.381</X><Y>-526.5127</Y></pos><radius>100</radius><mass>10000</mass><angle>0</angle><typeIndex>0</typeIndex></Planet><Planet><pos><X>2326.2996</X><Y>947.87976</Y></pos><radius>100</radius><mass>10000</mass><angle>0</angle><typeIndex>5</typeIndex></Planet><Planet><pos><X>4313.9614</X><Y>-136.82855</Y></pos><radius>100</radius><mass>10000</mass><angle>0</angle><typeIndex>2</typeIndex></Planet><Planet><pos><X>608.14624</X><Y>-99.010315</Y></pos><radius>100</radius><mass>10000</mass><angle>0</angle><typeIndex>0</typeIndex></Planet><Planet><pos><X>2469.2053</X><Y>-754.4386</Y></pos><radius>100</radius><mass>10000</mass><angle>0</angle><typeIndex>2</typeIndex></Planet><Planet><pos><X>2685.5469</X><Y>842.60986</Y></pos><radius>100</radius><mass>10000</mass><angle>0</angle><typeIndex>5</typeIndex></Planet><Planet><pos><X>5035.7495</X><Y>82.42334</Y></pos><radius>100</radius><mass>10000</mass><angle>0</angle><typeIndex>2</typeIndex></Planet><Planet><pos><X>1445.5703</X><Y>-767.31116</Y></pos><radius>100</radius><mass>10000</mass><angle>0</angle><typeIndex>2</typeIndex></Planet><Planet><pos><X>5486.8867</X><Y>-689.8855</Y></pos><radius>100</radius><mass>10000</mass><angle>0</angle><typeIndex>4</typeIndex></Planet><Planet><pos><X>792.52997</X><Y>-77.92279</Y></pos><radius>100</radius><mass>10000</mass><angle>0</angle><typeIndex>2</typeIndex></Planet><Planet><pos><X>1783.8788</X><Y>-129.0122</Y></pos><radius>100</radius><mass>10000</mass><angle>0</angle><typeIndex>3</typeIndex></Planet><Planet><pos><X>5487.707</X><Y>-680.194</Y></pos><radius>100</radius><mass>10000</mass><angle>0</angle><typeIndex>4</typeIndex></Planet><Planet><pos><X>2.9574432</X><Y>635.17615</Y></pos><radius>100</radius><mass>10000</mass><angle>0</angle><typeIndex>4</typeIndex></Planet><Planet><pos><X>5766.2563</X><Y>-919.37695</Y></pos><radius>100</radius><mass>10000</mass><angle>0</angle><typeIndex>0</typeIndex></Planet><Planet><pos><X>3511.5283</X><Y>-67.03027</Y></pos><radius>100</radius><mass>10000</mass><angle>0</angle><typeIndex>5</typeIndex></Planet><Planet><pos><X>883.1506</X><Y>-550.6903</Y></pos><radius>100</radius><mass>10000</mass><angle>0</angle><typeIndex>4</typeIndex></Planet><Planet><pos><X>3254.8945</X><Y>-36.0531</Y></pos><radius>100</radius><mass>10000</mass><angle>0</angle><typeIndex>3</typeIndex></Planet><Planet><pos><X>5182.4634</X><Y>801.7355</Y></pos><radius>100</radius><mass>10000</mass><angle>0</angle><typeIndex>0</typeIndex></Planet><Planet><pos><X>3774.2253</X><Y>885.27026</Y></pos><radius>100</radius><mass>10000</mass><angle>0</angle><typeIndex>0</typeIndex></Planet><Planet><pos><X>3918.7097</X><Y>-53.52893</Y></pos><radius>100</radius><mass>10000</mass><angle>0</angle><typeIndex>4</typeIndex></Planet><Planet><pos><X>472.8968</X><Y>173.81042</Y></pos><radius>100</radius><mass>10000</mass><angle>0</angle><typeIndex>5</typeIndex></Planet><Planet><pos><X>373.66147</X><Y>608.08923</Y></pos><radius>100</radius><mass>10000</mass><angle>0</angle><typeIndex>0</typeIndex></Planet><Planet><pos><X>2225.959</X><Y>-6.1671753</Y></pos><radius>100</radius><mass>10000</mass><angle>0</angle><typeIndex>5</typeIndex></Planet><Planet><pos><X>4347.5107</X><Y>-105.80347</Y></pos><radius>100</radius><mass>10000</mass><angle>0</angle><typeIndex>0</typeIndex></Planet><Planet><pos><X>1142.0555</X><Y>756.4977</Y></pos><radius>100</radius><mass>10000</mass><angle>0</angle><typeIndex>3</typeIndex></Planet><Planet><pos><X>1629.2054</X><Y>311.3474</Y></pos><radius>100</radius><mass>10000</mass><angle>0</angle><typeIndex>3</typeIndex></Planet><Planet><pos><X>3655.8518</X><Y>534.5786</Y></pos><radius>100</radius><mass>10000</mass><angle>0</angle><typeIndex>5</typeIndex></Planet><Planet><pos><X>590.1024</X><Y>179.21191</Y></pos><radius>100</radius><mass>10000</mass><angle>0</angle><typeIndex>5</typeIndex></Planet><Planet><pos><X>4407.095</X><Y>-132.86157</Y></pos><radius>100</radius><mass>10000</mass><angle>0</angle><typeIndex>3</typeIndex></Planet><Planet><pos><X>3251.2495</X><Y>-428.83948</Y></pos><radius>100</radius><mass>10000</mass><angle>0</angle><typeIndex>1</typeIndex></Planet><Planet><pos><X>3495.583</X><Y>-305.2508</Y></pos><radius>100</radius><mass>10000</mass><angle>0</angle><typeIndex>2</typeIndex></Planet><Planet><pos><X>4998.952</X><Y>764.4531</Y></pos><radius>100</radius><mass>10000</mass><angle>0</angle><typeIndex>2</typeIndex></Planet><Planet><pos><X>862.6014</X><Y>45.95569</Y></pos><radius>100</radius><mass>10000</mass><angle>0</angle><typeIndex>3</typeIndex></Planet><Planet><pos><X>4967.7563</X><Y>552.3971</Y></pos><radius>100</radius><mass>10000</mass><angle>0</angle><typeIndex>4</typeIndex></Planet><Planet><pos><X>4308.2036</X><Y>635.7947</Y></pos><radius>100</radius><mass>10000</mass><angle>0</angle><typeIndex>0</typeIndex></Planet><Planet><pos><X>2841.3682</X><Y>346.8026</Y></pos><radius>100</radius><mass>10000</mass><angle>0</angle><typeIndex>0</typeIndex></Planet><Planet><pos><X>3410.5403</X><Y>-284.9934</Y></pos><radius>100</radius><mass>10000</mass><angle>0</angle><typeIndex>1</typeIndex></Planet><Planet><pos><X>2723.2383</X><Y>-912.3807</Y></pos><radius>100</radius><mass>10000</mass><angle>0</angle><typeIndex>4</typeIndex></Planet><Planet><pos><X>5230.882</X><Y>960.9314</Y></pos><radius>100</radius><mass>10000</mass><angle>0</angle><typeIndex>5</typeIndex></Planet><Planet><pos><X>5848.8916</X><Y>-344.47778</Y></pos><radius>100</radius><mass>10000</mass><angle>0</angle><typeIndex>2</typeIndex></Planet><Planet><pos><X>2782.2493</X><Y>658.23645</Y></pos><radius>100</radius><mass>10000</mass><angle>0</angle><typeIndex>1</typeIndex></Planet><Planet><pos><X>4373.6587</X><Y>-716.0242</Y></pos><radius>100</radius><mass>10000</mass><angle>0</angle><typeIndex>0</typeIndex></Planet><Planet><pos><X>4456.1865</X><Y>-285.63232</Y></pos><radius>100</radius><mass>10000</mass><angle>0</angle><typeIndex>5</typeIndex></Planet><Planet><pos><X>184.96326</X><Y>-744.4653</Y></pos><radius>100</radius><mass>10000</mass><angle>0</angle><typeIndex>0</typeIndex></Planet></Planets><Bounds><X>-100</X><Y>-1000</Y><Width>6000</Width><Height>2000</Height><Location><X>-100</X><Y>-1000</Y></Location><Size><X>6000</X><Y>2000</Y></Size></Bounds><LevelID>9875</LevelID></Level>